streamlit_embedcode/__init__.py
streamlit_embedcode-0.1.1.dist-info/LICENSE
streamlit_embedcode-0.1.1.dist-info/METADATA
streamlit_embedcode-0.1.1.dist-info/WHEEL
streamlit_embedcode-0.1.1.dist-info/top_level.txt
streamlit_embedcode-0.1.1.dist-info/RECORD
