Metadata-Version: 2.1
Name: streamlit-embedcode
Version: 0.1.1
Summary: Streamlit component for embedded code snippets
Home-page: https://github.com/randyzwitch/streamlit-embedcode
Author: Randy Zwitch
Author-email: randy@streamlit.io
License: UNKNOWN
Platform: UNKNOWN
Requires-Python: >=3.6
Requires-Dist: streamlit (>=0.63)
